pyfsext.cpython-311-darwin.so
libfsext_python-20251107.dist-info/licenses/COPYING
libfsext_python-20251107.dist-info/licenses/COPYING.LESSER
libfsext_python-20251107.dist-info/METADATA
libfsext_python-20251107.dist-info/WHEEL
libfsext_python-20251107.dist-info/top_level.txt
libfsext_python-20251107.dist-info/RECORD
