Metadata-Version: 2.4
Name: libfsext-python
Version: 20251107
Summary: Python bindings module for libfsext
Author: Joachim Metz
Author-email: joachim.metz@gmail.com
License: GNU Lesser General Public License v3 or later (LGPLv3+)
Classifier: Development Status :: 2 - Pre-Alpha
Classifier: Programming Language :: Python
Requires-Python: >=3.8
License-File: COPYING
License-File: COPYING.LESSER
Dynamic: license-file
